allen_dataverse_client/__init__.py
allen_dataverse_client/api_client.py
allen_dataverse_client/api_response.py
allen_dataverse_client/configuration.py
allen_dataverse_client/exceptions.py
allen_dataverse_client/py.typed
allen_dataverse_client/rest.py
allen_dataverse_client/api/__init__.py
allen_dataverse_client/api/default_api.py
allen_dataverse_client/models/__init__.py
allen_dataverse_client/models/fetch_project_by_name_request.py
allen_dataverse_client/models/fetch_table_by_name_request.py
allen_dataverse_client-0.0.1.dist-info/METADATA
allen_dataverse_client-0.0.1.dist-info/WHEEL
allen_dataverse_client-0.0.1.dist-info/top_level.txt
allen_dataverse_client-0.0.1.dist-info/RECORD
